SuPerSim/__init__.py
SuPerSim/captions.py
SuPerSim/constants.py
SuPerSim/evolution.py
SuPerSim/functions_summary.py
SuPerSim/horizon.py
SuPerSim/legends.py
SuPerSim/model.py
SuPerSim/mytime.py
SuPerSim/open.py
SuPerSim/percentiles.py
SuPerSim/pickling.py
SuPerSim/plotblocks.py
SuPerSim/preparation.py
SuPerSim/runningstats.py
SuPerSim/seasonal.py
SuPerSim/topoheatmap.py
SuPerSim/weights.py
SuPerSim/yearlystats.py
supersim-1.2.0.dist-info/licenses/LICENSE
supersim-1.2.0.dist-info/METADATA
supersim-1.2.0.dist-info/WHEEL
supersim-1.2.0.dist-info/top_level.txt
supersim-1.2.0.dist-info/RECORD
