Metadata-Version: 2.4
Name: SuPerSim
Version: 1.2.0
Summary: Summary statistics and plots for ensemble Permafrost Simulations
Author-email: Victor Pozsgay <victorpozsgay@cunet.carleton.ca>
License: GNU GENERAL PUBLIC LICENSE
Project-URL: Homepage, https://github.com/VictorPozsgay/SuPerSim
Classifier: Programming Language :: Python :: 3
Classifier: License :: OSI Approved :: GNU General Public License v3 (GPLv3)
Classifier: Operating System :: POSIX :: Linux
Classifier: Topic :: Scientific/Engineering :: GIS
Classifier: Topic :: Scientific/Engineering :: Atmospheric Science
Requires-Python: >=3.7
License-File: LICENSE
Dynamic: license-file
